vihub/__init__.py
vihub/config.py
vihub/main.py
vihub-0.0.9.dist-info/METADATA
vihub-0.0.9.dist-info/WHEEL
vihub-0.0.9.dist-info/entry_points.txt
vihub-0.0.9.dist-info/top_level.txt
vihub-0.0.9.dist-info/RECORD
