Metadata-Version: 2.1
Name: vihub
Version: 0.0.9
Requires-Dist: requests
